{"nodes": [{"id": "ref_change_management", "label": "Change Management for L&D \u00e2\u20ac\u201d Coaching Scaffold", "file_type": "document", "source_file": "master-instructional-design/references/change-management.md", "source_location": null, "source_url": null, "captured_at": null, "author": "Norman Arosemena", "contributor": null}, {"id": "ref_change_adkar", "label": "ADKAR Mapped to L&D Interventions", "file_type": "document", "source_file": "master-instructional-design/references/change-management.md", "source_location": "line 17", "source_url": null, "captured_at": null, "author": null, "contributor": null}, {"id": "ref_change_resistance_types", "label": "Change Resistance Types & L&D Responses", "file_type": "document", "source_file": "master-instructional-design/references/change-management.md", "source_location": "line 30", "source_url": null, "captured_at": null, "author": null, "contributor": null}, {"id": "ref_change_champion_networks", "label": "Change Champion Networks", "file_type": "document", "source_file": "master-instructional-design/references/change-management.md", "source_location": "line 42", "source_url": null, "captured_at": null, "author": null, "contributor": null}, {"id": "ref_change_cannot_willnot", "label": "Cannot vs Will-Not Diagnostic", "file_type": "document", "source_file": "master-instructional-design/references/change-management.md", "source_location": "line 4", "source_url": null, "captured_at": null, "author": null, "contributor": null}, {"id": "concept_adkar_model", "label": "ADKAR Change Model (Prosci)", "file_type": "document", "source_file": "master-instructional-design/references/change-management.md", "source_location": null, "source_url": null, "captured_at": null, "author": "Prosci", "contributor": null}, {"id": "rationale_cannot_vs_willnot", "label": "Rationale: Cannot vs Will-Not Prevents Training-for-Desire Gap", "file_type": "document", "source_file": "master-instructional-design/references/change-management.md", "source_location": "line 4", "source_url": null, "captured_at": null, "author": "Norman Arosemena", "contributor": null}], "edges": [{"source": "ref_change_management", "target": "ref_change_adkar", "relation": "references", "confidence": "EXTRACTED", "confidence_score": 1.0, "source_file": "master-instructional-design/references/change-management.md", "source_location": "line 17", "weight": 1.0}, {"source": "ref_change_management", "target": "ref_change_resistance_types", "relation": "references", "confidence": "EXTRACTED", "confidence_score": 1.0, "source_file": "master-instructional-design/references/change-management.md", "source_location": "line 30", "weight": 1.0}, {"source": "ref_change_management", "target": "ref_change_champion_networks", "relation": "references", "confidence": "EXTRACTED", "confidence_score": 1.0, "source_file": "master-instructional-design/references/change-management.md", "source_location": "line 42", "weight": 1.0}, {"source": "ref_change_management", "target": "ref_change_cannot_willnot", "relation": "references", "confidence": "EXTRACTED", "confidence_score": 1.0, "source_file": "master-instructional-design/references/change-management.md", "source_location": "line 4", "weight": 1.0}, {"source": "ref_change_adkar", "target": "concept_adkar_model", "relation": "references", "confidence": "EXTRACTED", "confidence_score": 1.0, "source_file": "master-instructional-design/references/change-management.md", "source_location": "line 17", "weight": 1.0}, {"source": "rationale_cannot_vs_willnot", "target": "ref_change_cannot_willnot", "relation": "rationale_for", "confidence": "EXTRACTED", "confidence_score": 1.0, "source_file": "master-instructional-design/references/change-management.md", "source_location": "line 4", "weight": 1.0}, {"source": "concept_adkar_model", "target": "ref_hard_change", "relation": "conceptually_related_to", "confidence": "INFERRED", "confidence_score": 0.85, "source_file": "master-instructional-design/references/change-management.md", "source_location": null, "weight": 0.85}], "hyperedges": []}