{"nodes": [{"id": "soft_new_paradox", "label": "Soft-New Paradox Prior Competence as Barrier", "file_type": "document", "source_file": "master-instructional-design/references/soft-new.md", "source_location": null, "source_url": null, "captured_at": null, "author": "Norman Arosemena", "contributor": null}, {"id": "soft_new_prior_scaffolding_diagnostic", "label": "Soft-New Prior Scaffolding Diagnostic", "file_type": "document", "source_file": "master-instructional-design/references/soft-new.md", "source_location": null, "source_url": null, "captured_at": null, "author": "Norman Arosemena", "contributor": null}, {"id": "soft_new_reclassification_decision_tree", "label": "Soft-New Reclassification Decision Tree", "file_type": "document", "source_file": "master-instructional-design/references/soft-new.md", "source_location": null, "source_url": null, "captured_at": null, "author": "Norman Arosemena", "contributor": null}, {"id": "soft_new_heterogeneous_cohort", "label": "Soft-New Heterogeneous Cohort Expert Augmenter Model", "file_type": "document", "source_file": "master-instructional-design/references/soft-new.md", "source_location": null, "source_url": null, "captured_at": null, "author": "Norman Arosemena", "contributor": null}, {"id": "soft_new_cross_level_activity", "label": "Soft-New Cross-Level Pairs Activity Design", "file_type": "document", "source_file": "master-instructional-design/references/soft-new.md", "source_location": null, "source_url": null, "captured_at": null, "author": "Norman Arosemena", "contributor": null}], "edges": [{"source": "soft_new_paradox", "target": "soft_change_identity_threat", "relation": "conceptually_related_to", "confidence": "EXTRACTED", "confidence_score": 1.0, "source_file": "master-instructional-design/references/soft-new.md", "source_location": null, "weight": 1.0}, {"source": "soft_new_prior_scaffolding_diagnostic", "target": "soft_new_reclassification_decision_tree", "relation": "conceptually_related_to", "confidence": "EXTRACTED", "confidence_score": 1.0, "source_file": "master-instructional-design/references/soft-new.md", "source_location": null, "weight": 1.0}, {"source": "soft_new_reclassification_decision_tree", "target": "soft_change_design_pattern", "relation": "references", "confidence": "EXTRACTED", "confidence_score": 1.0, "source_file": "master-instructional-design/references/soft-new.md", "source_location": null, "weight": 1.0}, {"source": "soft_new_heterogeneous_cohort", "target": "soft_new_cross_level_activity", "relation": "conceptually_related_to", "confidence": "EXTRACTED", "confidence_score": 1.0, "source_file": "master-instructional-design/references/soft-new.md", "source_location": null, "weight": 1.0}], "hyperedges": []}